[
  {
    "chunk_id": "891f4438-f425-437b-b318-3da46c004bfc",
    "titre": "Formation Power BI",
    "content": "",
    "source": "Formation_Power_BI.json"
  },
  {
    "chunk_id": "7f0b7411-1767-4367-a116-0d53c5350b69",
    "titre": "Formation Power BI",
    "content": "Créer des tableaux de bord interactifs\nAnalyser les données de manière visuelle\nMaîtriser Power BI Service\n\nConnaissance de base en Excel\nNotions de bases en manipulation de données\n\nAnalystes de données\nDéveloppeurs\nToute personne souhaitant utiliser Power BI\n\nIntroduction à Power BI\nVisualisation des données\n\nAnalystes de données\nDéveloppeurs\nToute personne souhaitant utiliser Power BI\nConnaissance de base en Excel\nNotions de bases en manipulation de données\nCréer des tableaux de bord interactifs\nAnalyser les données de manière visuelle\nMaîtriser Power BI Service\nIntroduction à Power BI\nPrésentation de l'interface\nConnexions aux sources de données\nCréation de rapports simples\nVisualisation des données\nUtilisation des visuels\nFormatage et personnalisation\nMise en page des rapports",
    "source": "Formation_Power_BI.json"
  }
]